{
  "name": "wiroc-config",
  "version": "0.1.8",
  "title": "WiRoc Config",
  "description": "App used to configure WiRoc devices",
  "tags": [
    {
      "label": "ble",
      "type": "comm"
    }
  ],
  "libraries": [
    {
      "name": "jquery",
      "version": "2.1.1"
    }
  ],
  "index-file": "index.html",
  "uuid": "71813a26-ff93-4873-93af-5262f34ccfb5",
  "plugins": [
    {
      "name": "cordova-plugin-ble",
      "version": "2.0.1"
    },
    {
      "name": "cordova-plugin-http",
      "version": "v0.2.2"
    }
  ],
  "long-description": "App used to configure WiRoc devices",
  "author-name": "Henrik Larsson",
  "author-email": "laselase@gmail.com",
  "author-url": "https://github.com/henla464/WiRoc-Config/",
  "cordova-id": "com.evothings.samples.WiRoc.Config",
  "icon": "res/icon-512x512.png"
}